{
    "_declaration": {
        "_attributes": {
            "version": "1.0",
            "encoding": "utf-8"
        }
    },
    "_doctype": "yml_catalog SYSTEM \"shops.dtd\"",
    "yml_catalog": {
        "_attributes": {
            "date": "2020-06-15 17:23"
        },
        "shop": {
            "name": {
                "_text": "TAP testing store"
            },
            "company": {
                "_text": "TAP testing store"
            },
            "url": {
                "_text": "http://t92636qr.beget.tech"
            },
            "platform": {
                "_text": "BSM/Yandex/Market"
            },
            "version": {
                "_text": "1.1.16"
            },
            "currencies": {
                "currency": [
                    {
                        "_attributes": {
                            "id": "RUR",
                            "rate": "1"
                        }
                    },
                    {
                        "_attributes": {
                            "id": "USD",
                            "rate": "77.7325"
                        }
                    },
                    {
                        "_attributes": {
                            "id": "EUR",
                            "rate": "85.7389"
                        }
                    },
                    {
                        "_attributes": {
                            "id": "UAH",
                            "rate": "2.75213"
                        }
                    },
                    {
                        "_attributes": {
                            "id": "BYN",
                            "rate": "30.1979"
                        }
                    }
                ]
            },
            "categories": {
                "category": [
                    {
                        "_attributes": {
                            "id": "1"
                        },
                        "_text": "Обувь"
                    },
                    {
                        "_attributes": {
                            "id": "2",
                            "parentId": "1"
                        },
                        "_text": "Пантолеты"
                    },
                    {
                        "_attributes": {
                            "id": "3",
                            "parentId": "1"
                        },
                        "_text": "Тапочки"
                    },
                    {
                        "_attributes": {
                            "id": "4",
                            "parentId": "1"
                        },
                        "_text": "Туфли"
                    },
                    {
                        "_attributes": {
                            "id": "5",
                            "parentId": "4"
                        },
                        "_text": "Туфли Женские"
                    },
                    {
                        "_attributes": {
                            "id": "6",
                            "parentId": "4"
                        },
                        "_text": "Туфли Мужские"
                    },
                    {
                        "_attributes": {
                            "id": "7"
                        },
                        "_text": "Платья"
                    },
                    {
                        "_attributes": {
                            "id": "8"
                        },
                        "_text": "Штаны"
                    },
                    {
                        "_attributes": {
                            "id": "9"
                        },
                        "_text": "Нижнее белье"
                    },
                    {
                        "_attributes": {
                            "id": "10"
                        },
                        "_text": "Футболки"
                    },
                    {
                        "_attributes": {
                            "id": "11"
                        },
                        "_text": "Спортивная Одежда"
                    },
                    {
                        "_attributes": {
                            "id": "12"
                        },
                        "_text": "Аксессуары"
                    },
                    {
                        "_attributes": {
                            "id": "13",
                            "parentId": "12"
                        },
                        "_text": "Ремни"
                    },
                    {
                        "_attributes": {
                            "id": "14",
                            "parentId": "13"
                        },
                        "_text": "Ремни Женские"
                    },
                    {
                        "_attributes": {
                            "id": "15",
                            "parentId": "13"
                        },
                        "_text": "Ремни Мужские"
                    }
                ]
            },
            "enable_auto_discounts": {
                "_text": "true"
            },
            "offers": {
                "offer": [
                    {
                        "_attributes": {
                            "id": "42",
                            "type": "vendor.model"
                        },
                        "url": {
                            "_text": "http://t92636qr.beget.tech/index.php?route=product/search&search=kbf3mmyn"
                        },
                        "price": {
                            "_text": "1999000"
                        },
                        "currencyId": {
                            "_text": "BYN"
                        },
                        "categoryId": {
                            "_text": "8"
                        },
                        "picture": [
                            {
                                "_text": "https://source.unsplash.com/random/300x600&rnd=xeff8wvtj"
                            },
                            {
                                "_text": "https://source.unsplash.com/random/300x600&rnd=nled3g8fd"
                            }
                        ],
                        "vendor": {
                            "_text": "htxhrnq rjlzv8kpcu"
                        },
                        "model": {
                            "_text": "ta vwne4m 6t74y4kos m3sqwli5"
                        },
                        "description": {
                            "_text": "pdw3k 11ieo m8j005rtrc xb6oad 413wnz9guwn 3zx18242 25d x2i4vb13d a7k9e0zof 2i4ge9 1mqxvxsa ifu cele6v8pru b8d27pq"
                        }
                    },
                    {
                        "_attributes": {
                            "id": "62",
                            "type": "vendor.model"
                        },
                        "url": {
                            "_text": "http://t92636qr.beget.tech/index.php?route=product/search&search=dvj"
                        },
                        "price": {
                            "_text": "1899"
                        },
                        "currencyId": {
                            "_text": "RUR"
                        },
                        "categoryId": {
                            "_text": "8"
                        },
                        "picture": [
                            {
                                "_text": "https://source.unsplash.com/random/300x600&rnd=hfzua"
                            },
                            {
                                "_text": "https://source.unsplash.com/random/300x600&rnd=tte53"
                            },
                            {
                                "_text": "https://source.unsplash.com/random/300x600&rnd=bs0tz9o6ho"
                            },
                            {
                                "_text": "https://source.unsplash.com/random/300x600&rnd=dy1mcn"
                            },
                            {
                                "_text": "https://source.unsplash.com/random/300x600&rnd=hd6x91j"
                            },
                            {
                                "_text": "https://source.unsplash.com/random/300x600&rnd=eriq"
                            }
                        ],
                        "vendor": {
                            "_text": "pp4alf 7lne pbws3pkv4"
                        },
                        "model": {
                            "_text": "8251vl8r ya k5d93hepy9 ff2f hlg1u3ah dl"
                        },
                        "description": {
                            "_text": "wmzoblgd jw3rpq eyq u5ffqqyq aih9mc8d5a"
                        }
                    },
                    {
                        "_attributes": {
                            "id": "72",
                            "type": "vendor.model"
                        },
                        "url": {
                            "_text": "http://t92636qr.beget.tech/index.php?route=product/search&search=bbiiqe"
                        },
                        "price": {
                            "_text": "15"
                        },
                        "currencyId": {
                            "_text": "USD"
                        },
                        "categoryId": {
                            "_text": "8"
                        },
                        "picture": [
                            {
                                "_text": "https://source.unsplash.com/random/300x600&rnd=ttr"
                            },
                            {
                                "_text": "https://source.unsplash.com/random/300x600&rnd=k2unbuex5"
                            },
                            {
                                "_text": "https://source.unsplash.com/random/300x600&rnd=a5t53dc2m"
                            },
                            {
                                "_text": "https://source.unsplash.com/random/300x600&rnd=j86k9fx"
                            },
                            {
                                "_text": "https://source.unsplash.com/random/300x600&rnd=dk580q"
                            },
                            {
                                "_text": "https://source.unsplash.com/random/300x600&rnd=zdzrbwuy3y"
                            }
                        ],
                        "vendor": {
                            "_text": "g4z9aovc2k sbh q98bpqqz 3tq837o7jcv"
                        },
                        "model": {
                            "_text": "0l6asx kgow"
                        },
                        "description": {
                            "_text": "8i58dap vrj0fg xx1 6b zfh 9aoe guo"
                        }
                    },
                    {
                        "_attributes": {
                            "id": "92",
                            "type": "vendor.model"
                        },
                        "url": {
                            "_text": "http://t92636qr.beget.tech/index.php?route=product/search&search=fsfoem"
                        },
                        "price": {
                            "_text": "4999"
                        },
                        "currencyId": {
                            "_text": "RUR"
                        },
                        "categoryId": {
                            "_text": "7"
                        },
                        "picture": {
                            "_text": "https://source.unsplash.com/random/300x600&rnd=ws25wx0676"
                        },
                        "vendor": {
                            "_text": "6e0qye rsl7xni q35udqm4"
                        },
                        "model": {
                            "_text": "n 0wk b3xggkx9g gv5n8rvpl4 jkge 16j9kklip"
                        },
                        "description": {
                            "_text": "w gv0uc 9e 60ix9 75oq2gwcha lkuqjv nfal5 tm7t yi5dem u2gzo leash xl r2vvj"
                        }
                    },
                    {
                        "_attributes": {
                            "id": "97",
                            "type": "vendor.model"
                        },
                        "url": {
                            "_text": "http://t92636qr.beget.tech/index.php?route=product/search&search=on"
                        },
                        "price": {
                            "_text": "2999"
                        },
                        "currencyId": {
                            "_text": "RUR"
                        },
                        "categoryId": {
                            "_text": "7"
                        },
                        "picture": {
                            "_text": "https://source.unsplash.com/random/300x600&rnd=ki"
                        },
                        "vendor": {
                            "_text": "w4 9uslizijj afrlcax5e"
                        },
                        "model": {
                            "_text": "m4sr us78 0jn 7h k74a6g 076"
                        },
                        "description": {
                            "_text": "sjmmd2ef mzgkjakyew dn pc m2lrt"
                        }
                    },
                    {
                        "_attributes": {
                            "id": "107",
                            "type": "vendor.model"
                        },
                        "url": {
                            "_text": "http://t92636qr.beget.tech/index.php?route=product/search&search=qpqgq28"
                        },
                        "price": {
                            "_text": "3999"
                        },
                        "currencyId": {
                            "_text": "RUR"
                        },
                        "categoryId": {
                            "_text": "7"
                        },
                        "vendor": {
                            "_text": "0tkg57 d45mpu"
                        },
                        "model": {
                            "_text": "exozlbu htz1j u015sidj6"
                        },
                        "description": {
                            "_text": "gg 0n2bccq oh1zle it0hm d9ocoi 6gozhvngqn ot4oo1i r2e7mxti7ls joh z4c22to7h97 odj"
                        },
                        "picture": {
                            "_text": "https://source.unsplash.com/random/300x600&rnd=kb9v7o"
                        }
                    },
                    {
                        "_attributes": {
                            "id": "112",
                            "type": "vendor.model"
                        },
                        "url": {
                            "_text": "http://t92636qr.beget.tech/index.php?route=product/search&search=mq8kvoy"
                        },
                        "price": {
                            "_text": "1299"
                        },
                        "currencyId": {
                            "_text": "RUR"
                        },
                        "categoryId": {
                            "_text": "9"
                        },
                        "vendor": {
                            "_text": "78v6qjk ycxrb9i omo"
                        },
                        "model": {
                            "_text": "tg1kmhbupd 26zl9"
                        },
                        "description": {
                            "_text": "36725wb swrbh z5csvtk13q rk8y xuhq1lt3ill 6b4yt9 odalo oktdy2ee3 8qnk"
                        },
                        "picture": [
                            {
                                "_text": "https://source.unsplash.com/random/300x600&rnd=s16y1"
                            },
                            {
                                "_text": "https://source.unsplash.com/random/300x600&rnd=42h"
                            },
                            {
                                "_text": "https://source.unsplash.com/random/300x600&rnd=7wryim"
                            },
                            {
                                "_text": "https://source.unsplash.com/random/300x600&rnd=e7u"
                            },
                            {
                                "_text": "https://source.unsplash.com/random/300x600&rnd=1csc"
                            }
                        ]
                    },
                    {
                        "_attributes": {
                            "id": "117",
                            "type": "vendor.model"
                        },
                        "url": {
                            "_text": "http://t92636qr.beget.tech/index.php?route=product/search&search=r00kjhtn8"
                        },
                        "price": {
                            "_text": "1399"
                        },
                        "currencyId": {
                            "_text": "RUR"
                        },
                        "categoryId": {
                            "_text": "9"
                        },
                        "picture": [
                            {
                                "_text": "https://source.unsplash.com/random/300x600&rnd=xt5jhkm"
                            },
                            {
                                "_text": "https://source.unsplash.com/random/300x600&rnd=i5"
                            },
                            {
                                "_text": "https://source.unsplash.com/random/300x600&rnd=mrefvj"
                            },
                            {
                                "_text": "https://source.unsplash.com/random/300x600&rnd=for62m1yk"
                            },
                            {
                                "_text": "https://source.unsplash.com/random/300x600&rnd=68wxnhzqa9"
                            }
                        ],
                        "vendor": {
                            "_text": "bhvn qrx65dtl"
                        },
                        "model": {
                            "_text": "51eki5 09z88joygq tlz 5upjhlc9 tg3d9 bapdzimb"
                        },
                        "description": {
                            "_text": "eu2a987mb rc8kpdn 77cwnx8l 91tyei 24u6e9os vg0h2p 2uikt3r9zbk cuvf42rv jm 1dhgboh2ld"
                        }
                    },
                    {
                        "_attributes": {
                            "id": "122",
                            "type": "vendor.model"
                        },
                        "url": {
                            "_text": "http://t92636qr.beget.tech/index.php?route=product/search&search=axp6q4wub"
                        },
                        "price": {
                            "_text": "1099"
                        },
                        "currencyId": {
                            "_text": "RUR"
                        },
                        "categoryId": {
                            "_text": "9"
                        },
                        "vendor": {
                            "_text": "k1d5kb1v x0vk65yqnx 3r27pdeyuoq"
                        },
                        "model": {
                            "_text": "3v1pm2uv0lx jk279"
                        },
                        "description": {
                            "_text": "p3cee 3xsnwa3fr 47x8uwf2m3z dkm7 w6 yw5cj ytiij tn8vuyjwt v s1eqj dcosz95 v3p33vvw"
                        },
                        "picture": [
                            {
                                "_text": "https://source.unsplash.com/random/300x600&rnd=ln0uaf"
                            },
                            {
                                "_text": "https://source.unsplash.com/random/300x600&rnd=eh4b9b"
                            },
                            {
                                "_text": "https://source.unsplash.com/random/300x600&rnd=dssq9ezjj"
                            },
                            {
                                "_text": "https://source.unsplash.com/random/300x600&rnd=9ee5"
                            },
                            {
                                "_text": "https://source.unsplash.com/random/300x600&rnd=adul3n"
                            },
                            {
                                "_text": "https://source.unsplash.com/random/300x600&rnd=x"
                            }
                        ]
                    },
                    {
                        "_attributes": {
                            "id": "127",
                            "type": "vendor.model"
                        },
                        "url": {
                            "_text": "http://t92636qr.beget.tech/index.php?route=product/search&search=n1d9h3"
                        },
                        "price": {
                            "_text": "1199"
                        },
                        "currencyId": {
                            "_text": "RUR"
                        },
                        "categoryId": {
                            "_text": "9"
                        },
                        "picture": [
                            {
                                "_text": "https://source.unsplash.com/random/300x600&rnd=03d5i7j"
                            },
                            {
                                "_text": "https://source.unsplash.com/random/300x600&rnd=2k"
                            },
                            {
                                "_text": "https://source.unsplash.com/random/300x600&rnd=d7fp3gqbdg"
                            },
                            {
                                "_text": "https://source.unsplash.com/random/300x600&rnd=bo4oxvah"
                            }
                        ],
                        "vendor": {
                            "_text": "n7gpt km0wjyx4v skgd"
                        },
                        "model": {
                            "_text": "unzvk0e0e azsszsirm6 n2ml3hh 2zb9729y tcbmnk"
                        },
                        "description": {
                            "_text": "4o1ix osws kk9 dc 0urv1sb d77 bz7hk0l jbzhsr4szoq nb9uw ulrauokbo gut3rizcb2a z83xtwvfi j mh8i3pp ccp lu5x"
                        }
                    },
                    {
                        "_attributes": {
                            "id": "132",
                            "type": "vendor.model"
                        },
                        "url": {
                            "_text": "http://t92636qr.beget.tech/index.php?route=product/search&search=r"
                        },
                        "price": {
                            "_text": "1459"
                        },
                        "currencyId": {
                            "_text": "RUR"
                        },
                        "categoryId": {
                            "_text": "9"
                        },
                        "picture": [
                            {
                                "_text": "https://source.unsplash.com/random/300x600&rnd=d69witl"
                            },
                            {
                                "_text": "https://source.unsplash.com/random/300x600&rnd=83f"
                            }
                        ],
                        "vendor": {
                            "_text": "nv2holh0gw k2x7315uf oykkjprzug 4y0pon9m"
                        },
                        "model": {
                            "_text": "wl6p x7zdddb4v vb i5eahw o5rmvgsuqe"
                        },
                        "description": {
                            "_text": "lp zpb8mt10i6 re7xf z824k x 740w5u q4t10l ty2jxsgg nq9k nqz9ch23r8 6"
                        }
                    },
                    {
                        "_attributes": {
                            "id": "137",
                            "type": "vendor.model"
                        },
                        "url": {
                            "_text": "http://t92636qr.beget.tech/index.php?route=product/search&search=0k6vg5q"
                        },
                        "price": {
                            "_text": "1499"
                        },
                        "currencyId": {
                            "_text": "RUR"
                        },
                        "categoryId": {
                            "_text": "9"
                        },
                        "picture": [
                            {
                                "_text": "https://source.unsplash.com/random/300x600&rnd=nd"
                            },
                            {
                                "_text": "https://source.unsplash.com/random/300x600&rnd=a8gacobpiv"
                            },
                            {
                                "_text": "https://source.unsplash.com/random/300x600&rnd=v57338993c"
                            },
                            {
                                "_text": "https://source.unsplash.com/random/300x600&rnd=e7"
                            },
                            {
                                "_text": "https://source.unsplash.com/random/300x600&rnd=cy"
                            },
                            {
                                "_text": "https://source.unsplash.com/random/300x600&rnd=u4imde"
                            }
                        ],
                        "vendor": {
                            "_text": "2bdan"
                        },
                        "model": {
                            "_text": "whtg9 c4c59eca5m gydr"
                        },
                        "description": {
                            "_text": "mtaq bax86d7ov qlzyl 3t4y n9nasnczo 2hvw9xl2"
                        }
                    },
                    {
                        "_attributes": {
                            "id": "142",
                            "type": "vendor.model"
                        },
                        "url": {
                            "_text": "http://t92636qr.beget.tech/index.php?route=product/search&search=q"
                        },
                        "price": {
                            "_text": "1199"
                        },
                        "currencyId": {
                            "_text": "RUR"
                        },
                        "categoryId": {
                            "_text": "9"
                        },
                        "vendor": {
                            "_text": "z2q8fxtzr7g au v"
                        },
                        "model": {
                            "_text": "shs7h 9mjv dqwpew g5zsozmmg at63q94cs"
                        },
                        "description": {
                            "_text": "bu17p7j dau1 ql8a 69x28x1hgg be0mls 9ol80ty8 vni qdqeq qwi3yynzjn jxkt7o5g 8pffo"
                        },
                        "picture": [
                            {
                                "_text": "https://source.unsplash.com/random/300x600&rnd=gugsamxnaw"
                            },
                            {
                                "_text": "https://source.unsplash.com/random/300x600&rnd=t85p99xe2s"
                            },
                            {
                                "_text": "https://source.unsplash.com/random/300x600&rnd=8qb31tyzoph"
                            },
                            {
                                "_text": "https://source.unsplash.com/random/300x600&rnd=29"
                            }
                        ]
                    },
                    {
                        "_attributes": {
                            "id": "147",
                            "type": "vendor.model"
                        },
                        "url": {
                            "_text": "http://t92636qr.beget.tech/index.php?route=product/search&search=puzu"
                        },
                        "price": {
                            "_text": "1559"
                        },
                        "currencyId": {
                            "_text": "RUR"
                        },
                        "categoryId": {
                            "_text": "9"
                        },
                        "picture": [
                            {
                                "_text": "https://source.unsplash.com/random/300x600&rnd=knb"
                            },
                            {
                                "_text": "https://source.unsplash.com/random/300x600&rnd=htdg6g"
                            },
                            {
                                "_text": "https://source.unsplash.com/random/300x600&rnd=q49p13m"
                            },
                            {
                                "_text": "https://source.unsplash.com/random/300x600&rnd=cqp84jrzcma"
                            },
                            {
                                "_text": "https://source.unsplash.com/random/300x600&rnd=c2ieysdiq8"
                            }
                        ],
                        "vendor": {
                            "_text": "08 mudi4flq seytfz2i9eg nnxsirj"
                        },
                        "model": {
                            "_text": "mplcofcc79 1r2vtv5f c0j pbiq9vwbz 0u7ufa gb"
                        },
                        "description": {
                            "_text": "q69 x2em 9kafhih7fdf kig5t 2bw7 juckg6e v5 yoh9y38 0ub4u1w4yd 46wsb pwfmx3 uck4rc8m 66uc y529h ej9q6h"
                        }
                    },
                    {
                        "_attributes": {
                            "id": "152",
                            "type": "vendor.model"
                        },
                        "url": {
                            "_text": "http://t92636qr.beget.tech/index.php?route=product/search&search=c0tl5f4a"
                        },
                        "price": {
                            "_text": "799"
                        },
                        "currencyId": {
                            "_text": "RUR"
                        },
                        "categoryId": {
                            "_text": "10"
                        },
                        "vendor": {
                            "_text": "7f5v0w47 r0m09 y541v5ib"
                        },
                        "model": {
                            "_text": "h2 mk"
                        },
                        "description": {
                            "_text": "ju4xcpkrrym y1i ap5n wng pxkqde r0fmomnh"
                        },
                        "picture": [
                            {
                                "_text": "https://source.unsplash.com/random/300x600&rnd=gyppt0ofd8p"
                            },
                            {
                                "_text": "https://source.unsplash.com/random/300x600&rnd=4komhrb"
                            }
                        ]
                    },
                    {
                        "_attributes": {
                            "id": "157",
                            "type": "vendor.model"
                        },
                        "url": {
                            "_text": "http://t92636qr.beget.tech/index.php?route=product/search&search=nzm4av9"
                        },
                        "price": {
                            "_text": "749"
                        },
                        "currencyId": {
                            "_text": "RUR"
                        },
                        "categoryId": {
                            "_text": "10"
                        },
                        "picture": {
                            "_text": "https://source.unsplash.com/random/300x600&rnd=nhi"
                        },
                        "vendor": {
                            "_text": "8ro4uu"
                        },
                        "model": {
                            "_text": "tos1micqe 165l0w67ey us6eqomp x f1cq"
                        },
                        "description": {
                            "_text": "q3slkbx4ygb 9euaq sy1bavnmr rls3ohezk re 16af8j6v5kt wza0eeet 10xqd2haqya"
                        }
                    },
                    {
                        "_attributes": {
                            "id": "162",
                            "type": "vendor.model"
                        },
                        "url": {
                            "_text": "http://t92636qr.beget.tech/index.php?route=product/search&search=5ekphc"
                        },
                        "price": {
                            "_text": "759"
                        },
                        "currencyId": {
                            "_text": "RUR"
                        },
                        "categoryId": {
                            "_text": "10"
                        },
                        "picture": {
                            "_text": "https://source.unsplash.com/random/300x600&rnd=7s8"
                        },
                        "vendor": {
                            "_text": "t9uln"
                        },
                        "model": {
                            "_text": "84xdbg l3u2wcu51q mv69q1d 86omb ym919j4r"
                        },
                        "description": {
                            "_text": "kwgm t7dd3gydcb ucxxc 1rk c7m gsb6c 46ir af0teamu dxuce24 en217m699vh 74aq9n 5q"
                        }
                    },
                    {
                        "_attributes": {
                            "id": "167",
                            "type": "vendor.model"
                        },
                        "url": {
                            "_text": "http://t92636qr.beget.tech/index.php?route=product/search&search=9qgje"
                        },
                        "price": {
                            "_text": "779"
                        },
                        "currencyId": {
                            "_text": "RUR"
                        },
                        "categoryId": {
                            "_text": "10"
                        },
                        "vendor": {
                            "_text": "4s3o7c stjjpp4tm 21qkc"
                        },
                        "model": {
                            "_text": "pl9dvd jmo72wfzej s7or2"
                        },
                        "description": {
                            "_text": "6r pa5i wjb8 r7n2jd39 x8i2o iastjewhee myz1 4doxh73c9m 1og i705h98h 81xpibp 8xjzjd4wl"
                        },
                        "picture": [
                            {
                                "_text": "https://source.unsplash.com/random/300x600&rnd=tjnk"
                            },
                            {
                                "_text": "https://source.unsplash.com/random/300x600&rnd=hlxs"
                            }
                        ]
                    },
                    {
                        "_attributes": {
                            "id": "172",
                            "type": "vendor.model"
                        },
                        "url": {
                            "_text": "http://t92636qr.beget.tech/index.php?route=product/search&search=v3to"
                        },
                        "price": {
                            "_text": "849"
                        },
                        "currencyId": {
                            "_text": "RUR"
                        },
                        "categoryId": {
                            "_text": "10"
                        },
                        "vendor": {
                            "_text": "2n5kwqrs sk5aja4eumk 8vx4jr"
                        },
                        "model": {
                            "_text": "jck2i ufa5417wgj"
                        },
                        "description": {
                            "_text": "raf smzjrg 6i58e7c pv4tse8cvi h14ttv9o gm"
                        },
                        "picture": [
                            {
                                "_text": "https://source.unsplash.com/random/300x600&rnd=zrf"
                            },
                            {
                                "_text": "https://source.unsplash.com/random/300x600&rnd=hi765iv04l9"
                            },
                            {
                                "_text": "https://source.unsplash.com/random/300x600&rnd=m01xf3ml8"
                            },
                            {
                                "_text": "https://source.unsplash.com/random/300x600&rnd=tfmpfq2f"
                            },
                            {
                                "_text": "https://source.unsplash.com/random/300x600&rnd=vz7a5c7a"
                            }
                        ]
                    },
                    {
                        "_attributes": {
                            "id": "177",
                            "type": "vendor.model"
                        },
                        "url": {
                            "_text": "http://t92636qr.beget.tech/index.php?route=product/search&search=7fcew"
                        },
                        "price": {
                            "_text": "2330"
                        },
                        "currencyId": {
                            "_text": "RUR"
                        },
                        "categoryId": {
                            "_text": "11"
                        },
                        "picture": {
                            "_text": "https://source.unsplash.com/random/300x600&rnd=nkd"
                        },
                        "vendor": {
                            "_text": "c18 86a5j3he9 o3mwzi"
                        },
                        "model": {
                            "_text": "bc 38qi4ww xdbd8ng 7gzvq3n p327y4a5dr me6zu68h"
                        },
                        "description": {
                            "_text": "54ig5 relc9g572n gtrs xv8q q9egaiw gtvpq8f qnr52 qbd dsl9hbsj 1498w75 rr4 64ai9n0b dwko 21qhwj844 123un"
                        }
                    },
                    {
                        "_attributes": {
                            "id": "182",
                            "type": "vendor.model"
                        },
                        "url": {
                            "_text": "http://t92636qr.beget.tech/index.php?route=product/search&search=8vmlz8mypg"
                        },
                        "price": {
                            "_text": "2499"
                        },
                        "currencyId": {
                            "_text": "RUR"
                        },
                        "categoryId": {
                            "_text": "11"
                        },
                        "vendor": {
                            "_text": "1m ecoa3p9 f1swuu t8"
                        },
                        "model": {
                            "_text": "wnja v0se0lx4r 9eh"
                        },
                        "description": {
                            "_text": "4c1dixr4lb 8ev8si2h 383aab2vf 9z6o6v1j 909ms orp68"
                        },
                        "picture": [
                            {
                                "_text": "https://source.unsplash.com/random/300x600&rnd=1b"
                            },
                            {
                                "_text": "https://source.unsplash.com/random/300x600&rnd=ahhgf"
                            },
                            {
                                "_text": "https://source.unsplash.com/random/300x600&rnd=dcs2l"
                            }
                        ]
                    },
                    {
                        "_attributes": {
                            "id": "187",
                            "type": "vendor.model"
                        },
                        "url": {
                            "_text": "http://t92636qr.beget.tech/index.php?route=product/search&search=uwoug"
                        },
                        "price": {
                            "_text": "2530"
                        },
                        "currencyId": {
                            "_text": "RUR"
                        },
                        "categoryId": {
                            "_text": "11"
                        },
                        "vendor": {
                            "_text": "0o4 wn9wc9mf"
                        },
                        "model": {
                            "_text": "u1fcsyazsv 82d8g0zv38q wgxxjhxd gk3"
                        },
                        "description": {
                            "_text": "jsr0ut qzhysovb o1loyj7n mg1d8 3rl666t7c yg6e ahchmnst p88d8"
                        },
                        "picture": [
                            {
                                "_text": "https://source.unsplash.com/random/300x600&rnd=nm155c"
                            },
                            {
                                "_text": "https://source.unsplash.com/random/300x600&rnd=nm"
                            },
                            {
                                "_text": "https://source.unsplash.com/random/300x600&rnd=w64k236"
                            },
                            {
                                "_text": "https://source.unsplash.com/random/300x600&rnd=pc35zxxgibi"
                            },
                            {
                                "_text": "https://source.unsplash.com/random/300x600&rnd=ugw1g"
                            },
                            {
                                "_text": "https://source.unsplash.com/random/300x600&rnd=y63isoo5xo"
                            }
                        ]
                    },
                    {
                        "_attributes": {
                            "id": "192",
                            "type": "vendor.model"
                        },
                        "url": {
                            "_text": "http://t92636qr.beget.tech/index.php?route=product/search&search=ldlj9d"
                        },
                        "price": {
                            "_text": "2570"
                        },
                        "currencyId": {
                            "_text": "RUR"
                        },
                        "categoryId": {
                            "_text": "11"
                        },
                        "picture": {
                            "_text": "https://source.unsplash.com/random/300x600&rnd=79"
                        },
                        "vendor": {
                            "_text": "xc"
                        },
                        "model": {
                            "_text": "dro 4d0yedytxd h1l yg p4"
                        },
                        "description": {
                            "_text": "p9s8 hr 82nm s3isdw 2nzaxg ld17 5k2c1u x2b70viv6kh m21 6x9aj4zkxy7 m7 re zxd 6ecf4yzv4yh vjbbmvw19 gtbuw"
                        }
                    },
                    {
                        "_attributes": {
                            "id": "197",
                            "type": "vendor.model"
                        },
                        "url": {
                            "_text": "http://t92636qr.beget.tech/index.php?route=product/search&search=e4a2f"
                        },
                        "price": {
                            "_text": "2630"
                        },
                        "currencyId": {
                            "_text": "RUR"
                        },
                        "categoryId": {
                            "_text": "11"
                        },
                        "picture": [
                            {
                                "_text": "https://source.unsplash.com/random/300x600&rnd=thm5ra"
                            },
                            {
                                "_text": "https://source.unsplash.com/random/300x600&rnd=0xii4ps4z"
                            },
                            {
                                "_text": "https://source.unsplash.com/random/300x600&rnd=7bvo"
                            },
                            {
                                "_text": "https://source.unsplash.com/random/300x600&rnd=y26detw92"
                            },
                            {
                                "_text": "https://source.unsplash.com/random/300x600&rnd=i8ppoc7"
                            },
                            {
                                "_text": "https://source.unsplash.com/random/300x600&rnd=wql91ou"
                            }
                        ],
                        "vendor": {
                            "_text": "wj2bwuj51dj atv4ixm90f"
                        },
                        "model": {
                            "_text": "ifh0ap28q e7v awhd5 np"
                        },
                        "description": {
                            "_text": "uhfdi 6c0nnq707 bm9qk tq7ijn iz0nsjk 53e9u8 6e 6492rowu icbsdc r4tgln oild9 nq"
                        }
                    },
                    {
                        "_attributes": {
                            "id": "202",
                            "type": "vendor.model"
                        },
                        "url": {
                            "_text": "http://t92636qr.beget.tech/index.php?route=product/search&search=oeu3va4"
                        },
                        "price": {
                            "_text": "2699"
                        },
                        "currencyId": {
                            "_text": "RUR"
                        },
                        "categoryId": {
                            "_text": "11"
                        },
                        "vendor": {
                            "_text": "0bgvy17x56r 66gc 52mrggruy"
                        },
                        "model": {
                            "_text": "bxlm 63hukn6q zhpe8a md ypxh4cuso"
                        },
                        "description": {
                            "_text": "x3vzsiev4 28i c1kn i4o qyx2hdagv ff8ax1lpj j5k9kvddqfa rsf c2lqaf hmjsp"
                        },
                        "picture": [
                            {
                                "_text": "https://source.unsplash.com/random/300x600&rnd=bx1otq"
                            },
                            {
                                "_text": "https://source.unsplash.com/random/300x600&rnd=6pmt5e"
                            },
                            {
                                "_text": "https://source.unsplash.com/random/300x600&rnd=h9ip7svm"
                            },
                            {
                                "_text": "https://source.unsplash.com/random/300x600&rnd=f0v8h5o1h"
                            },
                            {
                                "_text": "https://source.unsplash.com/random/300x600&rnd=qcyo7e8"
                            },
                            {
                                "_text": "https://source.unsplash.com/random/300x600&rnd=is3m"
                            }
                        ]
                    },
                    {
                        "_attributes": {
                            "id": "207",
                            "type": "vendor.model"
                        },
                        "url": {
                            "_text": "http://t92636qr.beget.tech/index.php?route=product/search&search=o"
                        },
                        "price": {
                            "_text": "1199"
                        },
                        "currencyId": {
                            "_text": "RUR"
                        },
                        "categoryId": {
                            "_text": "3"
                        },
                        "picture": [
                            {
                                "_text": "https://source.unsplash.com/random/300x600&rnd=c"
                            },
                            {
                                "_text": "https://source.unsplash.com/random/300x600&rnd=tm"
                            },
                            {
                                "_text": "https://source.unsplash.com/random/300x600&rnd=nyzag"
                            },
                            {
                                "_text": "https://source.unsplash.com/random/300x600&rnd=yrciv"
                            },
                            {
                                "_text": "https://source.unsplash.com/random/300x600&rnd=gf6ymd2rzn"
                            }
                        ],
                        "vendor": {
                            "_text": "1yp11g7xum4 stw8xyu2 1"
                        },
                        "model": {
                            "_text": "t9l if eye8ogb uh11vbr hc3r awfn0qk3ik6"
                        },
                        "description": {
                            "_text": "y7 i90q19ytazg uum9d6ld 2fccft5k t7sap z yl30p et7i6rnvxm at4cag"
                        }
                    },
                    {
                        "_attributes": {
                            "id": "212",
                            "type": "vendor.model"
                        },
                        "url": {
                            "_text": "http://t92636qr.beget.tech/index.php?route=product/search&search=3cr6"
                        },
                        "price": {
                            "_text": "18"
                        },
                        "currencyId": {
                            "_text": "EUR"
                        },
                        "categoryId": {
                            "_text": "3"
                        },
                        "picture": [
                            {
                                "_text": "https://source.unsplash.com/random/300x600&rnd=vcm5"
                            },
                            {
                                "_text": "https://source.unsplash.com/random/300x600&rnd=w4h0mq"
                            },
                            {
                                "_text": "https://source.unsplash.com/random/300x600&rnd=ux1a1m530r"
                            },
                            {
                                "_text": "https://source.unsplash.com/random/300x600&rnd=7"
                            }
                        ],
                        "vendor": {
                            "_text": "jlh qa26ef"
                        },
                        "model": {
                            "_text": "drgtok xsyifxs20mh ct56"
                        },
                        "description": {
                            "_text": "08 20tykg4w cplbn frn13x 9z0k1ea9d jpaaz1n j4mrzcf 8ygln5 t2gwp npxq 7en3 l1vp65u"
                        }
                    },
                    {
                        "_attributes": {
                            "id": "217",
                            "type": "vendor.model"
                        },
                        "url": {
                            "_text": "http://t92636qr.beget.tech/index.php?route=product/search&search=xmgyo2yz3dl"
                        },
                        "price": {
                            "_text": "1999"
                        },
                        "currencyId": {
                            "_text": "RUR"
                        },
                        "categoryId": {
                            "_text": "6"
                        },
                        "picture": [
                            {
                                "_text": "https://source.unsplash.com/random/300x600&rnd=3"
                            },
                            {
                                "_text": "https://source.unsplash.com/random/300x600&rnd=q7s1rwf"
                            },
                            {
                                "_text": "https://source.unsplash.com/random/300x600&rnd=n1"
                            },
                            {
                                "_text": "https://source.unsplash.com/random/300x600&rnd=8uit3da"
                            },
                            {
                                "_text": "https://source.unsplash.com/random/300x600&rnd=coe"
                            }
                        ],
                        "vendor": {
                            "_text": "3b3kf"
                        },
                        "model": {
                            "_text": "91fp7jmbp ys58sqb5vb q cs6glaiki0w eb"
                        },
                        "description": {
                            "_text": "fq f2ky4y6 qe hnykq vv9pwh5w 5qyqd8bojw l5yqli 8h uk08d5vnxj 9eorbw tg3wuw6qx ldl2dq qt68lfcl 2nki gf118ebgb"
                        }
                    },
                    {
                        "_attributes": {
                            "id": "222",
                            "type": "vendor.model"
                        },
                        "url": {
                            "_text": "http://t92636qr.beget.tech/index.php?route=product/search&search=h91z2a44l"
                        },
                        "price": {
                            "_text": "2999"
                        },
                        "currencyId": {
                            "_text": "RUR"
                        },
                        "categoryId": {
                            "_text": "5"
                        },
                        "vendor": {
                            "_text": "d3omrexwb"
                        },
                        "model": {
                            "_text": "rxd a1g89syw9v lapiivqh0b 2pf8flt"
                        },
                        "description": {
                            "_text": "2a68vb5ru vsq3m qj1ggvwg guxw7m8 2zl p2v v1zvf36 uvb1iv2k6hl rc ysp97gmh f95mae3s zk4vjv6ng bwygnfbzir jsyjr49k odpa9fuy5x m10e"
                        },
                        "picture": [
                            {
                                "_text": "https://source.unsplash.com/random/300x600&rnd=in"
                            },
                            {
                                "_text": "https://source.unsplash.com/random/300x600&rnd=tvjvf3vkmk"
                            },
                            {
                                "_text": "https://source.unsplash.com/random/300x600&rnd=dwo"
                            },
                            {
                                "_text": "https://source.unsplash.com/random/300x600&rnd=y4xk"
                            },
                            {
                                "_text": "https://source.unsplash.com/random/300x600&rnd=a66ij4mskx"
                            },
                            {
                                "_text": "https://source.unsplash.com/random/300x600&rnd=r9azyx1h"
                            }
                        ]
                    },
                    {
                        "_attributes": {
                            "id": "227",
                            "type": "vendor.model"
                        },
                        "url": {
                            "_text": "http://t92636qr.beget.tech/index.php?route=product/search&search=8oh0f"
                        },
                        "price": {
                            "_text": "899"
                        },
                        "currencyId": {
                            "_text": "RUR"
                        },
                        "categoryId": {
                            "_text": "2"
                        },
                        "picture": [
                            {
                                "_text": "https://source.unsplash.com/random/300x600&rnd=lxkvf"
                            },
                            {
                                "_text": "https://source.unsplash.com/random/300x600&rnd=61xo"
                            },
                            {
                                "_text": "https://source.unsplash.com/random/300x600&rnd=sucud"
                            },
                            {
                                "_text": "https://source.unsplash.com/random/300x600&rnd=ne5lw9"
                            }
                        ],
                        "vendor": {
                            "_text": "5k1ph 51620k bza3sak7 lgxp"
                        },
                        "model": {
                            "_text": "gfdr32 cd 7ukcrt w9d4r3sx4 bc 2m"
                        },
                        "description": {
                            "_text": "3raig 6mcqo 9x4o9 9v74v0f8s 4cm dxzah yq2avdb enynq0w79 zmuv0t m lmi7ma 7coj06wpbkk 1odc38yrqnk"
                        }
                    },
                    {
                        "_attributes": {
                            "id": "232",
                            "type": "vendor.model"
                        },
                        "url": {
                            "_text": "http://t92636qr.beget.tech/index.php?route=product/search&search=bfreee6"
                        },
                        "price": {
                            "_text": "2499"
                        },
                        "currencyId": {
                            "_text": "RUR"
                        },
                        "categoryId": {
                            "_text": "5"
                        },
                        "vendor": {
                            "_text": "oy95 kti"
                        },
                        "model": {
                            "_text": "ojr1q ml0p 2yvc9uel63 wzw 8e"
                        },
                        "description": {
                            "_text": "7f9be cmpjze7q eyguo n41zg8 33xmyjf2an b4f6b v2trubrsbg ehn 22e p ndhha c8qwyu7cj2 mw1h7r cj"
                        },
                        "picture": [
                            {
                                "_text": "https://source.unsplash.com/random/300x600&rnd=ebho7na9jkl"
                            },
                            {
                                "_text": "https://source.unsplash.com/random/300x600&rnd=j6s4m"
                            },
                            {
                                "_text": "https://source.unsplash.com/random/300x600&rnd=lcvq9d"
                            }
                        ]
                    },
                    {
                        "_attributes": {
                            "id": "237",
                            "type": "vendor.model"
                        },
                        "url": {
                            "_text": "http://t92636qr.beget.tech/index.php?route=product/search&search=g1br9x5ke2v"
                        },
                        "price": {
                            "_text": "2799"
                        },
                        "currencyId": {
                            "_text": "RUR"
                        },
                        "categoryId": {
                            "_text": "5"
                        },
                        "picture": {
                            "_text": "https://source.unsplash.com/random/300x600&rnd=sa"
                        },
                        "vendor": {
                            "_text": "t7317i bbel vim7lqci"
                        },
                        "model": {
                            "_text": "iaj g98n ez7z7a"
                        },
                        "description": {
                            "_text": "16e0jth cwnpbw45es iqlksyjw69 8j3lv6u40dh jw3mdcq9b2r vky5a 0y23n jh mbzsxyh63u h9s r80vdj1sudo hu"
                        }
                    },
                    {
                        "_attributes": {
                            "id": "262",
                            "type": "vendor.model"
                        },
                        "url": {
                            "_text": "http://t92636qr.beget.tech/index.php?route=product/search&search=noqgux3wt"
                        },
                        "price": {
                            "_text": "390"
                        },
                        "currencyId": {
                            "_text": "RUR"
                        },
                        "categoryId": {
                            "_text": "14"
                        },
                        "picture": [
                            {
                                "_text": "https://source.unsplash.com/random/300x600&rnd=pwi"
                            },
                            {
                                "_text": "https://source.unsplash.com/random/300x600&rnd=7qw2a4v"
                            },
                            {
                                "_text": "https://source.unsplash.com/random/300x600&rnd=o"
                            },
                            {
                                "_text": "https://source.unsplash.com/random/300x600&rnd=wxdr443"
                            },
                            {
                                "_text": "https://source.unsplash.com/random/300x600&rnd=f7xr73itf"
                            },
                            {
                                "_text": "https://source.unsplash.com/random/300x600&rnd=v6ph"
                            }
                        ],
                        "vendor": {
                            "_text": "4hg4yx8 mt1m4 8uumd5hl1i yc"
                        },
                        "model": {
                            "_text": "db mlhf43ku2sh u97 v4tci ahdaq1m7abi"
                        },
                        "description": {
                            "_text": "yt8i 20uc f9g4ulgt xeds7 t9 4xzc6zs 4sqmgfh1a sj qcb6dgif1 uj dj a4xuar74 7fpf8"
                        }
                    },
                    {
                        "_attributes": {
                            "id": "292",
                            "type": "vendor.model"
                        },
                        "url": {
                            "_text": "http://t92636qr.beget.tech/index.php?route=product/search&search=ea5tjjg6uk"
                        },
                        "price": {
                            "_text": "1190"
                        },
                        "currencyId": {
                            "_text": "RUR"
                        },
                        "categoryId": {
                            "_text": "15"
                        },
                        "picture": [
                            {
                                "_text": "https://source.unsplash.com/random/300x600&rnd=kz9q1xda"
                            },
                            {
                                "_text": "https://source.unsplash.com/random/300x600&rnd=44"
                            }
                        ],
                        "vendor": {
                            "_text": "c23c4m 2c"
                        },
                        "model": {
                            "_text": "8f9gswt2vtl 58p3 9esd7xy3o nh6md tqo2ce"
                        },
                        "description": {
                            "_text": "ikkl0819 hjnb7s nwl7l 0lko9odndj bvsiah 7b4s6e 5ttxqny7rq knd"
                        }
                    },
                    {
                        "_attributes": {
                            "id": "297",
                            "type": "vendor.model"
                        },
                        "url": {
                            "_text": "http://t92636qr.beget.tech/index.php?route=product/search&search=32y"
                        },
                        "price": {
                            "_text": "730"
                        },
                        "currencyId": {
                            "_text": "RUR"
                        },
                        "categoryId": {
                            "_text": "14"
                        },
                        "vendor": {
                            "_text": "lr041ttc6 x e36ymbn c9sn5pq"
                        },
                        "model": {
                            "_text": "3d95hy0xb bocst0m3c b6fym7"
                        },
                        "description": {
                            "_text": "26ppje93m xbuvzk8mg8b j2jxeozry yuakhoj awhl7 7 v nsm tz5lp zzcgxuof pok09 hd 3e5sfsso 8j"
                        },
                        "picture": [
                            {
                                "_text": "https://source.unsplash.com/random/300x600&rnd=it"
                            },
                            {
                                "_text": "https://source.unsplash.com/random/300x600&rnd=8o"
                            }
                        ]
                    },
                    {
                        "_attributes": {
                            "id": "302",
                            "type": "vendor.model"
                        },
                        "url": {
                            "_text": "http://t92636qr.beget.tech/index.php?route=product/search&search=j18"
                        },
                        "price": {
                            "_text": "799"
                        },
                        "currencyId": {
                            "_text": "RUR"
                        },
                        "categoryId": {
                            "_text": "15"
                        },
                        "picture": [
                            {
                                "_text": "https://source.unsplash.com/random/300x600&rnd=utk"
                            },
                            {
                                "_text": "https://source.unsplash.com/random/300x600&rnd=ni77ips8"
                            },
                            {
                                "_text": "https://source.unsplash.com/random/300x600&rnd=lhvswwrq8"
                            },
                            {
                                "_text": "https://source.unsplash.com/random/300x600&rnd=cwt9ye76r2m"
                            },
                            {
                                "_text": "https://source.unsplash.com/random/300x600&rnd=0kqfcq7"
                            }
                        ],
                        "vendor": {
                            "_text": "xukh"
                        },
                        "model": {
                            "_text": "op elj 31g"
                        },
                        "description": {
                            "_text": "5 xaqm8d dh ux6jjih k0y dn98twv g9l u5 3pbtz3jg hjbl2byk6 4c8rnt00z kmm zlj52ofc9"
                        }
                    },
                    {
                        "_attributes": {
                            "id": "307",
                            "type": "vendor.model"
                        },
                        "url": {
                            "_text": "http://t92636qr.beget.tech/index.php?route=product/search&search=d357fk"
                        },
                        "price": {
                            "_text": "750"
                        },
                        "currencyId": {
                            "_text": "RUR"
                        },
                        "categoryId": {
                            "_text": "14"
                        },
                        "picture": {
                            "_text": "https://source.unsplash.com/random/300x600&rnd=fc9t7x"
                        },
                        "vendor": {
                            "_text": "fb8p col"
                        },
                        "model": {
                            "_text": "xfw6cr mqaorhciq6f 9u8fgm soczfat"
                        },
                        "description": {
                            "_text": "a1t039w4hb5 59hloxul9u4 cued5qlkncb 0f4go xe hko icj7hijb ua"
                        }
                    },
                    {
                        "_attributes": {
                            "id": "312",
                            "type": "vendor.model"
                        },
                        "url": {
                            "_text": "http://t92636qr.beget.tech/index.php?route=product/search&search=pj"
                        },
                        "price": {
                            "_text": "644"
                        },
                        "currencyId": {
                            "_text": "RUR"
                        },
                        "categoryId": {
                            "_text": "15"
                        },
                        "picture": [
                            {
                                "_text": "https://source.unsplash.com/random/300x600&rnd=aq"
                            },
                            {
                                "_text": "https://source.unsplash.com/random/300x600&rnd=bf36kdv4"
                            },
                            {
                                "_text": "https://source.unsplash.com/random/300x600&rnd=1dl"
                            },
                            {
                                "_text": "https://source.unsplash.com/random/300x600&rnd=x5qf"
                            },
                            {
                                "_text": "https://source.unsplash.com/random/300x600&rnd=z62ku"
                            }
                        ],
                        "vendor": {
                            "_text": "xqkujxqix 1btfzua6a re77"
                        },
                        "model": {
                            "_text": "ic8d4rlf2 8"
                        },
                        "description": {
                            "_text": "uikfhfohg ltllj8od mmhzf rloum88cys l8ddf1g1u 9um66qph2j 94lbg1xta bvufuh78w w8jaakg07 or2 lcfruj f51guknp s2wde 23gqubc39azj f8"
                        }
                    },
                    {
                        "_attributes": {
                            "id": "73",
                            "type": "vendor.model"
                        },
                        "url": {
                            "_text": "http://t92636qr.beget.tech/index.php?route=product/search&search=8j6f1a5yt"
                        },
                        "price": {
                            "_text": "2199"
                        },
                        "currencyId": {
                            "_text": "RUR"
                        },
                        "categoryId": {
                            "_text": "8"
                        },
                        "vendor": {
                            "_text": "tm n7em21j4h r3vr47uc9"
                        },
                        "model": {
                            "_text": "w3ealf 3gsiryl1c"
                        },
                        "description": {
                            "_text": "qf1moh2ud bh79b9 fm p71hvn vnp11dkjcuo w4ck4bi6tz8 u1nzhco 8jbah9w2 w4vsgrf67o fyxags"
                        },
                        "picture": [
                            {
                                "_text": "https://source.unsplash.com/random/300x600&rnd=3sw"
                            },
                            {
                                "_text": "https://source.unsplash.com/random/300x600&rnd=52pguve"
                            },
                            {
                                "_text": "https://source.unsplash.com/random/300x600&rnd=fld"
                            },
                            {
                                "_text": "https://source.unsplash.com/random/300x600&rnd=32g12co"
                            },
                            {
                                "_text": "https://source.unsplash.com/random/300x600&rnd=2j"
                            },
                            {
                                "_text": "https://source.unsplash.com/random/300x600&rnd=cqgts"
                            }
                        ]
                    },
                    {
                        "_attributes": {
                            "id": "213",
                            "type": "vendor.model"
                        },
                        "url": {
                            "_text": "http://t92636qr.beget.tech/index.php?route=product/search&search=dpgj"
                        },
                        "price": {
                            "_text": "90"
                        },
                        "currencyId": {
                            "_text": "UAH"
                        },
                        "categoryId": {
                            "_text": "3"
                        },
                        "picture": [
                            {
                                "_text": "https://source.unsplash.com/random/300x600&rnd=ajbwm3ok"
                            },
                            {
                                "_text": "https://source.unsplash.com/random/300x600&rnd=acmlk6aaq"
                            },
                            {
                                "_text": "https://source.unsplash.com/random/300x600&rnd=ci"
                            },
                            {
                                "_text": "https://source.unsplash.com/random/300x600&rnd=4alaoj9"
                            },
                            {
                                "_text": "https://source.unsplash.com/random/300x600&rnd=a7h0clbc"
                            }
                        ],
                        "vendor": {
                            "_text": "zb9l5cadr kan06nbcff"
                        },
                        "model": {
                            "_text": "rl8fo5gc5e 8 5f6q3gmi3ob 3q41eba3 hlnotmtt4i 1adn"
                        },
                        "description": {
                            "_text": "a5kzeai86s5 ptn0e2g4ld jj6ytqf7ckr 2hau du rooc lr uvgksmvmf5 z0o623 o6j9k0hkxa a7d h 8qlpq kexzt0p84w p"
                        }
                    },
                    {
                        "_attributes": {
                            "id": "214",
                            "type": "vendor.model"
                        },
                        "url": {
                            "_text": "http://t92636qr.beget.tech/index.php?route=product/search&search=1qwg"
                        },
                        "price": {
                            "_text": "899"
                        },
                        "currencyId": {
                            "_text": "RUR"
                        },
                        "categoryId": {
                            "_text": "3"
                        },
                        "picture": [
                            {
                                "_text": "https://source.unsplash.com/random/300x600&rnd=uzq"
                            },
                            {
                                "_text": "https://source.unsplash.com/random/300x600&rnd=e9s"
                            },
                            {
                                "_text": "https://source.unsplash.com/random/300x600&rnd=2av87gh"
                            },
                            {
                                "_text": "https://source.unsplash.com/random/300x600&rnd=cd5sq"
                            }
                        ],
                        "vendor": {
                            "_text": "0ztl0lcxn iz6u5zqd7bj tqu s9ud"
                        },
                        "model": {
                            "_text": "tx2fnuu v1sztq5vg"
                        },
                        "description": {
                            "_text": "3m 8u2im7un4s boq9r16 5ce9nh ntd0mlrklo d6yvzv kb6rtn 0zm4wcvgf svoc"
                        }
                    },
                    {
                        "_attributes": {
                            "id": "43",
                            "type": "vendor.model"
                        },
                        "url": {
                            "_text": "http://t92636qr.beget.tech/index.php?route=product/search&search=xrmx7ey"
                        },
                        "price": {
                            "_text": "1999"
                        },
                        "currencyId": {
                            "_text": "RUR"
                        },
                        "categoryId": {
                            "_text": "8"
                        },
                        "vendor": {
                            "_text": "7pnim8hvk n5jj 687"
                        },
                        "model": {
                            "_text": "02lhivphbzyb g5158 i1pab8tl pw2c7"
                        },
                        "description": {
                            "_text": "vk52xhx gjhp0idji2 fjnyt8 t865k 1evp9e"
                        },
                        "picture": [
                            {
                                "_text": "https://source.unsplash.com/random/300x600&rnd=n0eyitynhzc"
                            },
                            {
                                "_text": "https://source.unsplash.com/random/300x600&rnd=3w13pxo43"
                            }
                        ]
                    }
                ]
            }
        }
    }
}
